aipresenter/__init__.py
aipresenter/code_theme.py
aipresenter/formatter.py
aipresenter-0.1.0.dist-info/METADATA
aipresenter-0.1.0.dist-info/WHEEL
aipresenter-0.1.0.dist-info/top_level.txt
aipresenter-0.1.0.dist-info/RECORD
