Metadata-Version: 2.4
Name: aipresenter
Version: 0.1.0
Summary: A library to format raw AI responses into beautiful UI components.
Author-email: Shaik Janu <shaiksadikjanu@gmail.com>
License: MIT
Classifier: Programming Language :: Python :: 3
Classifier: License :: OSI Approved :: MIT License
Classifier: Operating System :: OS Independent
Requires-Python: >=3.7
Requires-Dist: markdown-it-py
Requires-Dist: pygments
